otpylib_config/__init__.py
otpylib_config/atoms.py
otpylib_config/boundaries.py
otpylib_config/client.py
otpylib_config/core.py
otpylib_config/data.py
otpylib_config/lifecycle.py
otpylib_config/sources/__init__.py
otpylib_config/sources/base.py
otpylib_config/sources/environment.py
otpylib_config/sources/file.py
otpylib_config/sources/runtime.py
otpylib_config-0.2.8.dist-info/METADATA
otpylib_config-0.2.8.dist-info/WHEEL
otpylib_config-0.2.8.dist-info/top_level.txt
otpylib_config-0.2.8.dist-info/RECORD
